repobee.py
_repobee/__init__.py
_repobee/__version.py
_repobee/colors.py
_repobee/config.py
_repobee/constants.py
_repobee/disthelpers.py
_repobee/distinfo.py
_repobee/exception.py
_repobee/fileutil.py
_repobee/formatters.py
_repobee/hash.py
_repobee/http.py
_repobee/main.py
_repobee/plugin.py
_repobee/urlutil.py
_repobee/cli/__init__.py
_repobee/cli/argparse_ext.py
_repobee/cli/dispatch.py
_repobee/cli/mainparser.py
_repobee/cli/parsing.py
_repobee/cli/pluginparsers.py
_repobee/cli/preparser.py
_repobee/command/__init__.py
_repobee/command/issues.py
_repobee/command/peer.py
_repobee/command/progresswrappers.py
_repobee/command/repos.py
_repobee/command/teams.py
_repobee/ext/__init__.py
_repobee/ext/ghclassroom.py
_repobee/ext/gitea.py
_repobee/ext/gitlab.py
_repobee/ext/javac.py
_repobee/ext/pairwise.py
_repobee/ext/pylint.py
_repobee/ext/query.py
_repobee/ext/squash.py
_repobee/ext/studentsyml.py
_repobee/ext/tamanager.py
_repobee/ext/core_commands/__init__.py
_repobee/ext/core_commands/_options.py
_repobee/ext/core_commands/repos.py
_repobee/ext/core_commands/teams.py
_repobee/ext/defaults/__init__.py
_repobee/ext/defaults/configwizard.py
_repobee/ext/defaults/genreviews.py
_repobee/ext/defaults/github.py
_repobee/ext/defaults/merge_configurable_args.py
_repobee/ext/defaults/students_file_parser.py
_repobee/ext/dist/__init__.py
_repobee/ext/dist/distmanager.py
_repobee/ext/dist/pluginmanager.py
_repobee/git/__init__.py
_repobee/git/_fetch.py
_repobee/git/_local.py
_repobee/git/_push.py
_repobee/git/_util.py
repobee-3.10.0.data/data/src/repobee_testhelpers/resources/.gitignore
repobee-3.10.0.data/data/src/repobee_testhelpers/resources/README.md
repobee-3.10.0.data/data/src/repobee_testhelpers/resources/students.txt
repobee_plug/__init__.py
repobee_plug/__version.py
repobee_plug/_corehooks.py
repobee_plug/_exthooks.py
repobee_plug/_featflags.py
repobee_plug/_immutable.py
repobee_plug/_pluginmeta.py
repobee_plug/config.py
repobee_plug/deprecation.py
repobee-3.10.0.dist-info/LICENSE
repobee-3.10.0.dist-info/METADATA
repobee-3.10.0.dist-info/WHEEL
repobee-3.10.0.dist-info/entry_points.txt
repobee-3.10.0.dist-info/top_level.txt
repobee-3.10.0.dist-info/RECORD
