Metadata-Version: 2.1
Name: repobee
Version: 3.10.0
Summary: A CLI tool for managing large amounts of GitHub repositories
Home-page: https://github.com/repobee/repobee
Author: Simon Larsén
Author-email: slarse@kth.se
License: MIT
Download-URL: https://github.com/repobee/repobee/archive/v3.10.0.tar.gz
Platform: UNKNOWN
Classifier: Development Status :: 5 - Production/Stable
Classifier: Intended Audience :: Education
Classifier: Programming Language :: Python :: 3.9
Classifier: Programming Language :: Python :: 3.10
Classifier: Programming Language :: Python :: 3.11
Classifier: Programming Language :: Python :: Implementation :: CPython
Classifier: License :: OSI Approved :: MIT License
Classifier: Operating System :: POSIX
Requires-Python: >=3.9
License-File: LICENSE
Requires-Dist: appdirs==1.4.4
Requires-Dist: argcomplete==3.4.0
Requires-Dist: bullet==2.2.0
Requires-Dist: daiquiri==3.2.5.1
Requires-Dist: gitpython==3.1.43
Requires-Dist: more-itertools==10.3.0
Requires-Dist: pluggy==1.5.0
Requires-Dist: pygithub==2.3.0
Requires-Dist: python-gitlab==4.6.0
Requires-Dist: tabulate==0.9.0
Requires-Dist: tqdm==4.66.4
Requires-Dist: yamliny==0.0.2
Provides-Extra: dev
Requires-Dist: bandit==1.7.8; extra == "dev"
Requires-Dist: black==24.4.2; extra == "dev"
Requires-Dist: flake8==7.0.0; extra == "dev"
Requires-Dist: mypy==1.10.0; extra == "dev"
Requires-Dist: pylint==3.1.0; extra == "dev"
Requires-Dist: pytest-cov==5.0.0; extra == "dev"
Requires-Dist: pytest-mock==3.14.0; extra == "dev"
Requires-Dist: pytest==8.2.0; extra == "dev"
Requires-Dist: virtualenv==20.26.1; extra == "dev"
Requires-Dist: sphinx-rtd-theme==2.0.0; extra == "dev"
Requires-Dist: responses==0.25.0; extra == "dev"
Requires-Dist: types-pkg-resources==0.1.3; extra == "dev"
Requires-Dist: types-requests==2.31.0.20240406; extra == "dev"
Requires-Dist: types-tabulate==0.9.0.20240106; extra == "dev"
Requires-Dist: types-toml==0.10.8.20240310; extra == "dev"
Requires-Dist: sphinx==7.3.7; extra == "dev"
Requires-Dist: sphinx-autodoc-typehints==2.1.0; extra == "dev"
Requires-Dist: sphinx-argparse==0.4.0; extra == "dev"
